pdf2mbox.py
pdf2mbox-0.3.4.dist-info/LICENSE
pdf2mbox-0.3.4.dist-info/METADATA
pdf2mbox-0.3.4.dist-info/WHEEL
pdf2mbox-0.3.4.dist-info/top_level.txt
pdf2mbox-0.3.4.dist-info/RECORD
