Metadata-Version: 2.1
Name: pdf2mbox
Version: 0.3.4
Summary: Extracts email metadata and text from a PDF file
Home-page: https://history-lab.github.io/pdf2mbox/
Author: Ben Lis, History Lab @ Columbia University
License: MIT License
Platform: UNKNOWN
Requires-Python: >=3.8
License-File: LICENSE
Requires-Dist: xmpdf
Requires-Dist: python-magic
